distributed_eaas_apis/__init__.py
distributed_eaas_apis/endpoint.py
distributed_eaas_apis/schema/__init__.py
distributed_eaas_apis/schema/bleu.py
distributed_eaas_apis/schema/common.py
distributed_eaas_apis/schema/rouge.py
distributed_eaas_apis-0.1.0.dist-info/METADATA
distributed_eaas_apis-0.1.0.dist-info/WHEEL
distributed_eaas_apis-0.1.0.dist-info/top_level.txt
distributed_eaas_apis-0.1.0.dist-info/RECORD
