Metadata-Version: 2.1
Name: distributed-eaas-apis
Version: 0.1.0
Summary: "Public API definitions of Distributed EaaS."
Home-page: UNKNOWN
License: Apache License 2.0
Keywords: eaas
Platform: UNKNOWN
Classifier: License :: OSI Approved :: Apache Software License
Classifier: Operating System :: OS Independent
Classifier: Programming Language :: Python :: 3
Classifier: Programming Language :: Python :: 3.8
Classifier: Programming Language :: Python :: 3.9
Classifier: Programming Language :: Python :: 3.10
Requires-Python: >=3.8
Requires-Dist: pydantic (>=1.9)
